{
  "data": {
    "episodes": {
      "results": [
        { "id": "16", "name": "Get Schwifty", "air_date": "August 23, 2015", "episode": "S02E05" },
        { "id": "17", "name": "The Ricks Must Be Crazy", "air_date": "August 30, 2015", "episode": "S02E06" },
        { "id": "18", "name": "Big Trouble in Little Sanchez", "air_date": "September 13, 2015", "episode": "S02E07" },
        { "id": "19", "name": "Interdimensional Cable 2", "air_date": "September 20, 2015", "episode": "S02E08" },
        { "id": "20", "name": "Look Who’s Purging Now", "air_date": "September 27, 2015", "episode": "S02E09" }
      ]
    }
  }
}
